flasc/__init__.py
flasc/_flasc.py
flasc/_flasc_branches.py
flasc/_flasc_depths.cpython-313-x86_64-linux-gnu.so
flasc/_flasc_depths.pyx
flasc/_hdbscan.py
flasc/_sklearn.py
flasc/plots.py
flasc/prediction.py
flasc/tests/__init__.py
flasc/tests/test_flasc.py
pyflasc-0.1.4.dist-info/METADATA
pyflasc-0.1.4.dist-info/WHEEL
pyflasc-0.1.4.dist-info/top_level.txt
pyflasc-0.1.4.dist-info/RECORD
pyflasc-0.1.4.dist-info/licenses/LICENSE
