Metadata-Version: 2.4
Name: pyflasc
Version: 0.1.4
Summary: Flare-Sensitive Clustering based on HDBSCAN*.
Author-email: Jelmer Bot <jelmer.bot@uhasselt.be>
License-Expression: BSD-3-Clause
Project-URL: Homepage, https://github.com/vda-lab/pyflasc
Project-URL: Issues, https://github.com/vda-lab/pyflasc/issues
Keywords: clustering,machine learning
Classifier: Development Status :: 5 - Production/Stable
Classifier: Intended Audience :: Science/Research
Classifier: Topic :: Scientific/Engineering
Classifier: Topic :: Scientific/Engineering :: Visualization
Classifier: Natural Language :: English
Classifier: Operating System :: OS Independent
Classifier: Programming Language :: Cython
Classifier: Programming Language :: Python :: 3 :: Only
Requires-Python: >=3.10
License-File: LICENSE
Requires-Dist: numpy<3,>=1.20
Requires-Dist: scipy<2,>=1.9
Requires-Dist: scikit-learn<2,>=1.6
Requires-Dist: joblib<2,>=1.1
Requires-Dist: hdbscan<1,>=0.8.41
Provides-Extra: tests
Requires-Dist: pytest; extra == "tests"
Requires-Dist: networkx>=3; extra == "tests"
Requires-Dist: matplotlib>=3.8; extra == "tests"
Requires-Dist: pygraphviz>=1; extra == "tests"
Requires-Dist: pandas>=2.2; extra == "tests"
Provides-Extra: docs
Requires-Dist: sphinx>=8; extra == "docs"
Requires-Dist: nbsphinx>=0.9; extra == "docs"
Requires-Dist: sphinx_rtd_theme>=2.0; extra == "docs"
Requires-Dist: matplotlib>=3.8; extra == "docs"
Provides-Extra: notebooks
Requires-Dist: pandas>=2.2; extra == "notebooks"
Requires-Dist: jupyterlab>=4; extra == "notebooks"
Requires-Dist: seaborn>=0.12; extra == "notebooks"
Requires-Dist: matplotlib>=3.4; extra == "notebooks"
Requires-Dist: pygraphviz>=1; extra == "notebooks"
Requires-Dist: networkx>=3; extra == "notebooks"
Requires-Dist: lensed_umap>=0.1; extra == "notebooks"
Requires-Dist: umap-learn>=0.5; extra == "notebooks"
Requires-Dist: tqdm>=4.62.3; extra == "notebooks"
Dynamic: license-file
